CHANGES.txt
MANIFEST.in
README.rst
setup.py
django_image/__init__.py
django_image/backend.py
django_image/settings.py
django_image.egg-info/PKG-INFO
django_image.egg-info/SOURCES.txt
django_image.egg-info/dependency_links.txt
django_image.egg-info/requires.txt
django_image.egg-info/top_level.txt
django_image/templatetags/__init__.py
django_image/templatetags/images.py
django_image/tests/__init__.py
django_image/tests/backend.py
django_image/tests/test_templatetags.py
example/__init__.py
example/manage.py
example/settings.py
example/urls.py
example/wsgi.py