Metadata-Version: 1.0
Name: django-image
Version: 0.1.0
Summary: Simple pluggable framework for displaying images in Django
Home-page: http://github.com/adamcharnock/django-image
Author: Adam Charnock
Author-email: adam@adamcharnock.com
License: MIT
Platform: UNKNOWN
